jupyter_ssh/__init__.py
jupyter_ssh/__main__.py
jupyter_ssh/_version.py
jupyter_ssh/application.py
jupyter_ssh/serverapplication.py
jupyter_ssh/handlers/__init__.py
jupyter_ssh/handlers/base.py
jupyter_ssh/handlers/config/__init__.py
jupyter_ssh/handlers/config/handler.py
jupyter_ssh/handlers/docker/__init__.py
jupyter_ssh/handlers/docker/handler.py
jupyter_ssh/handlers/echo/__init__.py
jupyter_ssh/handlers/echo/handler.py
jupyter_ssh/handlers/index/__init__.py
jupyter_ssh/handlers/index/handler.py
jupyter_ssh/handlers/ping/__init__.py
jupyter_ssh/handlers/ping/handler.py
jupyter_ssh/handlers/proxy/__init__.py
jupyter_ssh/handlers/proxy/handler.py
jupyter_ssh/handlers/relay/__init__.py
jupyter_ssh/handlers/relay/handler.py
jupyter_ssh/static/102.jupyter-ssh.js
jupyter_ssh/static/1020.jupyter-ssh.js
jupyter_ssh/static/1050.jupyter-ssh.js
jupyter_ssh/static/1110.jupyter-ssh.js
jupyter_ssh/static/1146.jupyter-ssh.js
jupyter_ssh/static/1292.jupyter-ssh.js
jupyter_ssh/static/1450.jupyter-ssh.js
jupyter_ssh/static/1626.jupyter-ssh.js
jupyter_ssh/static/1629.jupyter-ssh.js
jupyter_ssh/static/1696.jupyter-ssh.js
jupyter_ssh/static/1810.jupyter-ssh.js
jupyter_ssh/static/1900.jupyter-ssh.js
jupyter_ssh/static/1919.jupyter-ssh.js
jupyter_ssh/static/1956.jupyter-ssh.js
jupyter_ssh/static/2.jupyter-ssh.js
jupyter_ssh/static/2003.jupyter-ssh.js
jupyter_ssh/static/2030.jupyter-ssh.js
jupyter_ssh/static/2066.jupyter-ssh.js
jupyter_ssh/static/2074.jupyter-ssh.js
jupyter_ssh/static/2086.jupyter-ssh.js
jupyter_ssh/static/2148.jupyter-ssh.js
jupyter_ssh/static/2218.jupyter-ssh.js
jupyter_ssh/static/2322.jupyter-ssh.js
jupyter_ssh/static/2464.jupyter-ssh.js
jupyter_ssh/static/2529.jupyter-ssh.js
jupyter_ssh/static/2548.jupyter-ssh.js
jupyter_ssh/static/2579.jupyter-ssh.js
jupyter_ssh/static/2604.jupyter-ssh.js
jupyter_ssh/static/2610.jupyter-ssh.js
jupyter_ssh/static/2707.jupyter-ssh.js
jupyter_ssh/static/2839.jupyter-ssh.js
jupyter_ssh/static/2939.jupyter-ssh.js
jupyter_ssh-0.0.4.dist-info/METADATA
jupyter_ssh-0.0.4.dist-info/WHEEL
jupyter_ssh-0.0.4.dist-info/entry_points.txt
jupyter_ssh-0.0.4.dist-info/licenses/LICENSE
jupyter_ssh-0.0.4.dist-info/RECORD
