Metadata-Version: 2.1
Name: jupyter_ssh
Version: 0.0.4
Summary: 🪐 💻 Jupyter SSH.
Project-URL: Homepage, https://github.com/datalayer/jupyter-ssh
Project-URL: Bug Tracker, https://github.com/datalayer/jupyter-ssh/issues
Project-URL: Repository, https://github.com/datalayer/jupyter-ssh.git
Author-email: Datalayer <info@datalayer.io>
License: BSD 3-Clause License
License-File: LICENSE
Classifier: Framework :: Jupyter
Classifier: Framework :: Jupyter :: JupyterLab
Classifier: Framework :: Jupyter :: JupyterLab :: 4
Classifier: Framework :: Jupyter :: JupyterLab :: Extensions
Classifier: Framework :: Jupyter :: JupyterLab :: Extensions :: Prebuilt
Classifier: Intended Audience :: Developers
Classifier: Intended Audience :: Science/Research
Classifier: Intended Audience :: System Administrators
Classifier: License :: OSI Approved :: BSD License
Classifier: Programming Language :: Python
Classifier: Programming Language :: Python :: 3
Classifier: Programming Language :: Python :: 3.11
Requires-Python: >=3.11
Requires-Dist: docker
Requires-Dist: jupyter-server<3,>=2
Provides-Extra: test
Requires-Dist: coverage; extra == 'test'
Requires-Dist: pytest; extra == 'test'
Requires-Dist: pytest-asyncio; extra == 'test'
Requires-Dist: pytest-cov; extra == 'test'
Requires-Dist: pytest-jupyter; extra == 'test'
Requires-Dist: pytest-tornasync; extra == 'test'
